AUTHORS
LICENCE
MANIFEST.in
README.md
setup.py
django_file_serve_view.egg-info/PKG-INFO
django_file_serve_view.egg-info/SOURCES.txt
django_file_serve_view.egg-info/dependency_links.txt
django_file_serve_view.egg-info/not-zip-safe
django_file_serve_view.egg-info/top_level.txt
fileserveview/__init__.py
fileserveview/views.py