Metadata-Version: 1.0
Name: django-file-serve-view
Version: 0.0.3
Summary: Tiny file-serving class-based view (CBV) for Django
Home-page: https://github.com/joncombe/django-file-serve-view
Author: Jon Combe
Author-email: pypi@joncombe.net
License: BSD licence, see LICENCE file
Platform: UNKNOWN
